kinactive/__about__.py
kinactive/__init__.py
kinactive/config.py
kinactive/db.py
kinactive/distances.py
kinactive/features.py
kinactive/io.py
kinactive/model.py
kinactive/resources/Pkinase.hmm
kinactive/resources/__init__.py
kinactive/resources/tk2pk.json
kinactive/resources/models/DFG_classifier/in_classifier/features.txt
kinactive/resources/models/DFG_classifier/in_classifier/model.bin
kinactive/resources/models/DFG_classifier/in_classifier/params.json
kinactive/resources/models/DFG_classifier/in_classifier/targets.txt
kinactive/resources/models/DFG_classifier/meta_classifier/features.txt
kinactive/resources/models/DFG_classifier/meta_classifier/model.bin
kinactive/resources/models/DFG_classifier/meta_classifier/params.json
kinactive/resources/models/DFG_classifier/meta_classifier/targets.txt
kinactive/resources/models/DFG_classifier/other_classifier/features.txt
kinactive/resources/models/DFG_classifier/other_classifier/model.bin
kinactive/resources/models/DFG_classifier/other_classifier/params.json
kinactive/resources/models/DFG_classifier/other_classifier/targets.txt
kinactive/resources/models/DFG_classifier/out_classifier/features.txt
kinactive/resources/models/DFG_classifier/out_classifier/model.bin
kinactive/resources/models/DFG_classifier/out_classifier/params.json
kinactive/resources/models/DFG_classifier/out_classifier/targets.txt
kinactive/resources/models/kinactive_classifier/features.txt
kinactive/resources/models/kinactive_classifier/model.bin
kinactive/resources/models/kinactive_classifier/params.json
kinactive/resources/models/kinactive_classifier/targets.txt
kinactive-0.1.dist-info/METADATA
kinactive-0.1.dist-info/WHEEL
kinactive-0.1.dist-info/entry_points.txt
kinactive-0.1.dist-info/RECORD
